nodeum_sdk/__init__.py
nodeum_sdk/api_client.py
nodeum_sdk/configuration.py
nodeum_sdk/exceptions.py
nodeum_sdk/rest.py
nodeum_sdk/api/__init__.py
nodeum_sdk/api/cloud_buckets_api.py
nodeum_sdk/api/cloud_connectors_api.py
nodeum_sdk/api/containers_api.py
nodeum_sdk/api/files_api.py
nodeum_sdk/api/metadata_api.py
nodeum_sdk/api/mounts_api.py
nodeum_sdk/api/nas_api.py
nodeum_sdk/api/nas_shares_api.py
nodeum_sdk/api/pools_api.py
nodeum_sdk/api/statistics_api.py
nodeum_sdk/api/systems_api.py
nodeum_sdk/api/tape_drives_api.py
nodeum_sdk/api/tape_libraries_api.py
nodeum_sdk/api/tapes_api.py
nodeum_sdk/api/task_callbacks_api.py
nodeum_sdk/api/task_destinations_api.py
nodeum_sdk/api/task_executions_api.py
nodeum_sdk/api/task_metadata_api.py
nodeum_sdk/api/task_options_api.py
nodeum_sdk/api/task_schedules_api.py
nodeum_sdk/api/task_sources_api.py
nodeum_sdk/api/tasks_api.py
nodeum_sdk/api/users_api.py
nodeum_sdk/models/__init__.py
nodeum_sdk/models/active_job_status.py
nodeum_sdk/models/api_key.py
nodeum_sdk/models/api_key_collection.py
nodeum_sdk/models/api_key_full.py
nodeum_sdk/models/api_key_full_all_of.py
nodeum_sdk/models/api_key_scope.py
nodeum_sdk/models/attribute_error.py
nodeum_sdk/models/blank.py
nodeum_sdk/models/by_date_facet.py
nodeum_sdk/models/by_date_facet_bucket.py
nodeum_sdk/models/by_date_facet_bucket_all_of.py
nodeum_sdk/models/by_date_facet_buckets.py
nodeum_sdk/models/by_file_extension_facet.py
nodeum_sdk/models/by_file_extension_facet_all_of.py
nodeum_sdk/models/by_group_owner_facet.py
nodeum_sdk/models/by_group_owner_facet_all_of.py
nodeum_sdk/models/by_metadata_bucket.py
nodeum_sdk/models/by_metadata_bucket_all_of.py
nodeum_sdk/models/by_metadata_facet.py
nodeum_sdk/models/by_metadata_facet_all_of.py
nodeum_sdk/models/by_metadata_key_bucket.py
nodeum_sdk/models/by_metadata_key_bucket_all_of.py
nodeum_sdk/models/by_metadata_key_buckets.py
nodeum_sdk/models/by_metadata_value_buckets.py
nodeum_sdk/models/by_primary_cloud_facet.py
nodeum_sdk-1.88.0.dist-info/LICENSE
nodeum_sdk-1.88.0.dist-info/METADATA
nodeum_sdk-1.88.0.dist-info/WHEEL
nodeum_sdk-1.88.0.dist-info/top_level.txt
nodeum_sdk-1.88.0.dist-info/RECORD
