Metadata-Version: 2.1
Name: nodeum-sdk
Version: 1.88.0
Summary: Nodeum API
Home-page: UNKNOWN
Author: Nodeum
Author-email: info@nodeum.io
License: UNKNOWN
Keywords: OpenAPI,OpenAPI-Generator,Nodeum API
Platform: UNKNOWN
Requires-Dist: urllib3 (>=1.15)
Requires-Dist: six (>=1.10)
Requires-Dist: certifi
Requires-Dist: python-dateutil
